catleg/__init__.py
catleg/catleg.py
catleg/check_expiry.py
catleg/cli_util.py
catleg/config.py
catleg/find_changes.py
catleg/git_diff.py
catleg/law_text_fr.py
catleg/parse_catala_markdown.py
catleg/query.py
catleg/skeleton.py
catleg/markdown_it/heading_extension.py
catleg-0.2.8.dist-info/METADATA
catleg-0.2.8.dist-info/WHEEL
catleg-0.2.8.dist-info/entry_points.txt
catleg-0.2.8.dist-info/licenses/LICENSE
catleg-0.2.8.dist-info/RECORD
