Metadata-Version: 2.1
Name: catleg
Version: 0.2.8
Summary: A library of helper tools for catala programming in the context of French legislative texts.
Project-URL: Homepage, https://github.com/CatalaLang/catleg/
Project-URL: Bug Tracker, https://github.com/CatalaLang/catleg/issues
License:                                  Apache License
License-File: LICENSE
Classifier: License :: OSI Approved :: Apache Software License
Classifier: Operating System :: OS Independent
Classifier: Programming Language :: Python :: 3
Requires-Python: >=3.10
Requires-Dist: aiometer
Requires-Dist: dynaconf
Requires-Dist: httpx
Requires-Dist: markdown-it-py[plugins]
Requires-Dist: markdownify
Requires-Dist: mdformat>=0.7.16
Requires-Dist: more-itertools
Requires-Dist: typer[all]>=0.9.0
Requires-Dist: typing-extensions
Provides-Extra: dev
Requires-Dist: hatch; extra == 'dev'
Requires-Dist: mypy; extra == 'dev'
Requires-Dist: myst-parser; extra == 'dev'
Requires-Dist: pre-commit; extra == 'dev'
Requires-Dist: pytest; extra == 'dev'
Requires-Dist: ruff; extra == 'dev'
Requires-Dist: sphinx; extra == 'dev'
Requires-Dist: sphinx-rtd-theme; extra == 'dev'
Requires-Dist: tox; extra == 'dev'
